ipy_llm_kernel/__init__.py
ipy_llm_kernel/__main__.py
ipy_llm_kernel/_endpoints.py
ipy_llm_kernel/_kernel.py
ipy_llm_kernel/_tests/__init__.py
ipy_llm_kernel-0.2.0.dist-info/LICENSE
ipy_llm_kernel-0.2.0.dist-info/METADATA
ipy_llm_kernel-0.2.0.dist-info/WHEEL
ipy_llm_kernel-0.2.0.dist-info/top_level.txt
ipy_llm_kernel-0.2.0.dist-info/RECORD
