Metadata-Version: 2.1
Name: ipy-llm-kernel
Version: 0.2.0
Summary: A Jupyter kernel for communicating with large language models
Home-page: https://github.com/haesleinhuepf/ipy-llm-kernel
Author: Robert Haase
Author-email: robert.haase@uni-leipzig.de
License: BSD-3-Clause
Project-URL: Bug Tracker, https://github.com/haesleinhuepf/ipy-llm-kernel/issues
Project-URL: Documentation, https://github.com/haesleinhuepf/ipy-llm-kernel#README.md
Project-URL: Source Code, https://github.com/haesleinhuepf/ipy-llm-kernel
Project-URL: User Support, https://github.com/haesleinhuepf/ipy-llm-kernel/issues
Classifier: Development Status :: 2 - Pre-Alpha
Classifier: Intended Audience :: Developers
Classifier: License :: OSI Approved :: BSD License
Classifier: Operating System :: OS Independent
Classifier: Programming Language :: Python
Classifier: Programming Language :: Python :: 3
Classifier: Programming Language :: Python :: 3 :: Only
Classifier: Programming Language :: Python :: 3.8
Classifier: Programming Language :: Python :: 3.9
Classifier: Programming Language :: Python :: 3.10
Classifier: Topic :: Scientific/Engineering :: Image Processing
Requires-Python: >=3.9
License-File: LICENSE
Requires-Dist: numpy
Requires-Dist: ipython
Requires-Dist: jupyter-client
Requires-Dist: metakernel
Requires-Dist: openai>=1.30.1
Requires-Dist: anthropic>=0.30.1
Requires-Dist: google-generativeai
Requires-Dist: stackview
Requires-Dist: scikit-image
Provides-Extra: testing
Requires-Dist: tox; extra == "testing"
Requires-Dist: pytest; extra == "testing"
Requires-Dist: pytest-cov; extra == "testing"
